target_hotglue/__init__.py
target_hotglue/auth.py
target_hotglue/client.py
target_hotglue/common.py
target_hotglue/lambda.py
target_hotglue/rest.py
target_hotglue/sinks.py
target_hotglue/target.py
target_hotglue/target_base.py
target_hotglue/tests/__init__.py
target_hotglue/tests/test_core.py
target_hotglue-0.1.8.dist-info/METADATA
target_hotglue-0.1.8.dist-info/WHEEL
target_hotglue-0.1.8.dist-info/RECORD
